{
  "ActivityManagerShellCommand runStartActivity printwriter pw": "0.2681083",
  "ActivityManagerShellCommand runToUri printwriter pw int flags": "0.26588356",
  "ActivityManagerShellCommand runSendBroadcast printwriter pw": "0.2594455",
  "ActivityManagerShellCommand runCompact printwriter pw": "0.2594455",
  "ActivityManagerShellCommand runFreeze printwriter pw": "0.2594455",
  "ActivityManagerShellCommand runUnfreeze printwriter pw": "0.2594455",
  "ActivityManagerShellCommand getOutPrintWriter printwriter pw": "0.2594455",
  "ActivityManagerShellCommand runTraceIpc printwriter pw": "0.2594455",
  "ActivityManagerShellCommand runProfile printwriter pw": "0.2594455",
  "ActivityManagerShellCommand runDumpHeap printwriter pw": "0.2594455"
}